agentsts/core/__init__.py
agentsts/core/_actor_service.py
agentsts/core/_base.py
agentsts/core/client/__init__.py
agentsts/core/client/_client.py
agentsts/core/client/_config.py
agentsts/core/client/_exceptions.py
agentsts/core/client/_models.py
agentsts/core/client/_utils.py
agentsts_core-0.0.8.dist-info/METADATA
agentsts_core-0.0.8.dist-info/WHEEL
agentsts_core-0.0.8.dist-info/RECORD
