Metadata-Version: 2.4
Name: agentsts-core
Version: 0.0.8
Summary: Security Token Service client implementing RFC 8693 OAuth 2.0 Token Exchange
Requires-Python: >=3.11.0
Requires-Dist: cryptography>=41.0.0
Requires-Dist: httpx>=0.25.0
Requires-Dist: pydantic>=2.5.0
Requires-Dist: pyjwt>=2.8.0
Requires-Dist: typing-extensions>=4.8.0
Provides-Extra: test
Requires-Dist: pytest-asyncio>=0.21.0; extra == 'test'
Requires-Dist: pytest-mock>=3.0.0; extra == 'test'
Requires-Dist: pytest>=7.0.0; extra == 'test'
